py_colorgen/__init__.py
py_colorgen/colorgen.py
py_colorgen-0.1.0.dist-info/entry_points.txt
py_colorgen-0.1.0.dist-info/WHEEL
py_colorgen-0.1.0.dist-info/METADATA
py_colorgen-0.1.0.dist-info/RECORD
